sparkhub/__init__.py
sparkhub/_version.py
sparkhub/cloud_utils.py
sparkhub/gcloud.py
sparkhub/gcp.py
sparkhub/hadoopio.py
sparkhub/hailrunner.py
sparkhub/slackconnector.py
sparkhub/submit.py
sparkhub-0.3.0.2.dist-info/LICENSE.md
sparkhub-0.3.0.2.dist-info/METADATA
sparkhub-0.3.0.2.dist-info/WHEEL
sparkhub-0.3.0.2.dist-info/entry_points.txt
sparkhub-0.3.0.2.dist-info/top_level.txt
sparkhub-0.3.0.2.dist-info/RECORD
