Metadata-Version: 2.1
Name: sparkhub
Version: 0.3.0.2
Summary: Cloud utilities for running Hail systematically.
Home-page: https://github.com/TarjinderSingh/pycloud
Author: Tarjinder Singh
Author-email: tarjinder.s@gmail.com
License: MIT License
Requires-Python: >=3.7
License-File: LICENSE.md
Requires-Dist: versioneer ==0.29
Requires-Dist: loguru
Requires-Dist: hail >=0.2.45
Requires-Dist: slack-sdk
